Workbook

Sheet README
A1: AI Personal Finance Assistant - Database v1
A3: How to use
A4: Yellow cells | B4: Your inputs (Settings values, budget amounts).
A5: Blue text | B5: EXAMPLE data. Delete every row marked EXAMPLE before entering real data.
A6: Black cells | B6: Formulas. Do not overwrite.
A7: Entering expenses | B7: Type them on Transactions. Leave Transaction_ID blank; the script will assign IDs. Amounts are always positive.
A8: Changing month | B8: Settings > Report_Month controls Summary, Budgets and Commitments status.
A10: Transaction types
A11: Income | B11: Salary, bonus, freelance, gifts received. Counts as income.
A12: Expense | B12: Consumption spending. Counts toward budgets and spending.
A13: Refund | B13: Money returned for an earlier expense. Reduces that category's spending.
A14: Debt Payment | B14: Loan/credit card repayment. Not consumption; reduces cash. Use Expense for installments on goods you want counted as spending.
A15: Savings Transfer | B15: Cash moved to savings (e.g. certificate, savings account). Not spending, not income.
A16: Investment Contribution | B16: Cash sent to Thndr or another investment account. Not spending. Record purchases inside Thndr on the Investment_Transactions tab only.
A17: Investment Withdrawal | B17: Cash taken out of Thndr back to your bank. Not income.
A18: Investment Return | B18: Dividends/interest paid out to your cash accounts. Tracked separately, not salary income.
A19: Internal Transfer | B19: Moving money between your own cash accounts (e.g. ATM withdrawal). Ignored in income and spending.
A21: Double-counting rules
A22: Thndr | B22: Money leaving your bank for Thndr = one Investment Contribution on Transactions. What you buy inside Thndr goes ONLY on Investment_Transactions.
A23: ATM / own accounts | B23: Internal Transfer. Spending the cash later is recorded as normal Expenses.
A24: Refunds | B24: Refund with the original Transaction_ID in Related_Transaction_ID; reduces that category's spending.
A25: Commitments | B25: Record the payment as an Expense with Recurring_Flag = Yes and the Commitment_ID (e.g. CMT-001) in Related_Transaction_ID.
A26: Not built yet | B26: Account balances from transactions, anomaly flags, bot, dashboard, reports - later phases.

Sheet Settings
A1: Setting | B1: Value | C1: Description
A2: Time_Zone | B2: Africa/Cairo | C2: All dates and times use Egyptian local time.
A3: Currency | B3: EGP | C3: Primary currency.
A4: Report_Month | B4: 46296 | C4: First day of the month that Summary and Budgets calculate. Change this to view another month.
A5: Monthly_Salary | B5: 30000 | C5: EXAMPLE VALUE - replace with your net monthly salary.
A6: Salary_Day | B6: 25 | C6: EXAMPLE VALUE - day of month your salary usually arrives.
A7: Min_Cash_Buffer | B7: 5000 | C7: EXAMPLE VALUE - cash you always want to keep untouched, in EGP.
A8: Emergency_Fund_Months | B8: 6 | C8: EXAMPLE VALUE - months of expenses your emergency fund should cover.
A9: Budget_Warning_Pct | B9: 0.8 | C9: A category shows 'Warning' once spending reaches this share of its budget.
A10: Unusual_Txn_Multiplier | B10: 3 | C10: A single expense larger than this many times its category's average is flagged for review (not as an error).
A11: MoM_Increase_Alert_Pct | B11: 0.25 | C11: Flag categories whose spending rises more than this vs. the previous month.
A12: Confirmation_Mode | B12: ON | C12: ON = bot asks before saving; OFF = saves clear transactions immediately.
A13: Report_Email | C13: Email address for the monthly report.
A14: Report_Day | B14: 1 | C14: Day of month the report is generated for the previous month.
A15: Risk_Profile | C15: To be set later: Conservative / Moderate / Growth.

Sheet Summary
A1: Monthly Summary
A2: Month start | B2: =Settings!$B$4 -> 46296 | C2: From Settings > Report_Month
A3: Month end | B3: =EOMONTH(B2,0) -> 46326
A4: Today | B4: =TODAY() -> 46307
A5: Days in month | B5: =DAY(B3) -> 31
A6: Days elapsed | B6: =IF(B4<B2,0,MIN(B4,B3)-B2+1) -> 12 | C6: Full month once the month is over; 0 for a future month.
A8: INCOME
A9: Salary received | B9: =SUMIFS(Transactions!$E$2:$E$5000,Transactions!$D$2:$D$5000,"Income",Transactions!$B$2:$B$5000,">="&$B$2,Transactions!$B$2:$B$5000,"<="&$B$3,Transactions!$G$2:$G$5000,"Salary") -> 0 | C9: Income rows with Category = Salary.
A10: Additional income | B10: =SUMIFS(Transactions!$E$2:$E$5000,Transactions!$D$2:$D$5000,"Income",Transactions!$B$2:$B$5000,">="&$B$2,Transactions!$B$2:$B$5000,"<="&$B$3)-B9 -> 0 | C10: All other Income rows.
A11: Total income | B11: =B9+B10 -> 0 | C11: Excludes refunds, transfers, investment withdrawals and returns.
A13: SPENDING
A14: Gross expenses | B14: =SUMIFS(Transactions!$E$2:$E$5000,Transactions!$D$2:$D$5000,"Expense",Transactions!$B$2:$B$5000,">="&$B$2,Transactions!$B$2:$B$5000,"<="&$B$3) -> 10420
A15: Refunds | B15: =SUMIFS(Transactions!$E$2:$E$5000,Transactions!$D$2:$D$5000,"Refund",Transactions!$B$2:$B$5000,">="&$B$2,Transactions!$B$2:$B$5000,"<="&$B$3) -> 300
A16: Net consumption expenses | B16: =B14-B15 -> 10120 | C16: Gross expenses minus refunds. The one spending number used everywhere.
A17: Fixed commitments paid | B17: =SUMIFS(Transactions!$E$2:$E$5000,Transactions!$D$2:$D$5000,"Expense",Transactions!$B$2:$B$5000,">="&$B$2,Transactions!$B$2:$B$5000,"<="&$B$3,Transactions!$M$2:$M$5000,"Yes")-SUMIFS(Transactions!$E$2:$E$5000,Transactions!$D$2:$D$5000,"Refund",Transactions!$B$2:$B$5000,">="&$B$2,Transactions!$B$2:$B$5000,"<="&$B$3,Transactions!$M$2:$M$5000,"Yes") -> 8450 | C17: Expenses flagged Recurring_Flag = Yes.
A18: Variable expenses | B18: =B16-B17 -> 1670
A19: Debt payments | B19: =SUMIFS(Transactions!$E$2:$E$5000,Transactions!$D$2:$D$5000,"Debt Payment",Transactions!$B$2:$B$5000,">="&$B$2,Transactions!$B$2:$B$5000,"<="&$B$3) -> 0 | C19: Not consumption; still a cash outflow.
A20: Daily average spending | B20: =IF(B6=0,0,B16/B6) -> 843.33333 | C20: Net consumption / days elapsed.
A21: Commitments still due this month | B21: =SUM(Commitments!$M$2:$M$101) -> 3800 | C21: Active commitments not yet fully paid.
A22: Projected month-end spending | B22: =IF(B6=0,0,B17+B21+B18/B6*B5) -> 16564.167 | C22: Fixed paid + commitments still due + variable spending projected straight-line.
A24: SAVING AND INVESTING
A25: Savings transfers | B25: =SUMIFS(Transactions!$E$2:$E$5000,Transactions!$D$2:$D$5000,"Savings Transfer",Transactions!$B$2:$B$5000,">="&$B$2,Transactions!$B$2:$B$5000,"<="&$B$3) -> 2000
A26: Investment contributions | B26: =SUMIFS(Transactions!$E$2:$E$5000,Transactions!$D$2:$D$5000,"Investment Contribution",Transactions!$B$2:$B$5000,">="&$B$2,Transactions!$B$2:$B$5000,"<="&$B$3) -> 3000 | C26: Cash sent to Thndr. Purchases inside Thndr are NOT counted here.
A27: Investment withdrawals | B27: =SUMIFS(Transactions!$E$2:$E$5000,Transactions!$D$2:$D$5000,"Investment Withdrawal",Transactions!$B$2:$B$5000,">="&$B$2,Transactions!$B$2:$B$5000,"<="&$B$3) -> 0
A28: Investment returns paid out | B28: =SUMIFS(Transactions!$E$2:$E$5000,Transactions!$D$2:$D$5000,"Investment Return",Transactions!$B$2:$B$5000,">="&$B$2,Transactions!$B$2:$B$5000,"<="&$B$3) -> 0 | C28: Shown separately; not part of income.
A29: Net saved and invested | B29: =B25+B26-B27 -> 5000
A31: CASH FLOW
A32: Available cash flow | B32: =B11-B16-B19+B28 -> -10120 | C32: Income - net consumption - debt payments + investment returns.
A33: Cash flow after saving and investing | B33: =B32-B29 -> -15120 | C33: What stayed in your cash accounts this month.
A34: Uncommitted cash (estimate) | B34: =B33-B21-Settings!$B$7 -> -23920 | C34: After commitments still due and your minimum cash buffer. Negative = do not invest more this month.
A36: RATES
A37: Savings rate | B37: =IF(B11=0,0,(B11-B16-B19)/B11) -> 0 | C37: (Total income - net consumption - debt payments) / total income. Same definition in dashboard and report.
A38: Saved and invested rate | B38: =IF(B11=0,0,B29/B11) -> 0 | C38: Net saved and invested / total income. Money actually moved away from spending.
A40: COMPARISONS
A41: Previous month net consumption | B41: =SUMIFS(Transactions!$E$2:$E$5000,Transactions!$D$2:$D$5000,"Expense",Transactions!$B$2:$B$5000,">="&EDATE($B$2,-1),Transactions!$B$2:$B$5000,"<="&EOMONTH($B$2,-1))-SUMIFS(Transactions!$E$2:$E$5000,Transactions!$D$2:$D$5000,"Refund",Transactions!$B$2:$B$5000,">="&EDATE($B$2,-1),Transactions!$B$2:$B$5000,"<="&EOMONTH($B$2,-1)) -> 12200
A42: 3-month average (previous 3 full months) | B42: =(SUMIFS(Transactions!$E$2:$E$5000,Transactions!$D$2:$D$5000,"Expense",Transactions!$B$2:$B$5000,">="&EDATE($B$2,-3),Transactions!$B$2:$B$5000,"<="&EOMONTH($B$2,-1))-SUMIFS(Transactions!$E$2:$E$5000,Transactions!$D$2:$D$5000,"Refund",Transactions!$B$2:$B$5000,">="&EDATE($B$2,-3),Transactions!$B$2:$B$5000,"<="&EOMONTH($B$2,-1)))/3 -> 4066.6667 | C42: Includes months with no data as zero; meaningful once you have 3 months recorded.
A43: Change vs previous month (pace-adjusted) | B43: =IF(OR(B41=0,B6=0),0,(B16/B6*B5)/B41-1) -> 1.1428962 | C43: Compares this month's pace (projected to a full month) with last month's total, so an incomplete month is not unfairly low.
A44: Budget used (total) | B44: =Budgets!$E$17 -> 0.34421769

Sheet Transactions
A1: Transaction_ID | B1: Transaction_Date | C1: Transaction_Time | D1: Transaction_Type | E1: Amount | F1: Currency | G1: Category | H1: Subcategory | I1: Description | J1: Payment_Method | K1: Account | L1: Merchant | M1: Recurring_Flag | N1: Related_Transaction_ID | O1: Source | P1: Created_At | Q1: Updated_At | R1: Notes
A2: EX-0001 | B2: 46290 | C2: 0.375 | D2: Income | E2: 30000 | F2: EGP | G2: Salary | H2: Monthly Salary | I2: September salary | J2: Bank Transfer | K2: ACC-BANK1 | L2: Employer | M2: Yes | O2: Example | P2: 46290.375 | R2: EXAMPLE ROW - delete before entering real data
A3: EX-0002 | B3: 46292 | C3: 0.59027778 | D3: Expense | E3: 8000 | F3: EGP | G3: Housing | H3: Rent | I3: Monthly rent | J3: Bank Transfer | K3: ACC-BANK1 | L3: Landlord | M3: Yes | N3: CMT-001 | O3: Example | P3: 46292.59 | R3: EXAMPLE ROW - delete before entering real data
A4: EX-0003 | B4: 46293 | C4: 0.8125 | D4: Expense | E4: 4200 | F4: EGP | G4: Household | H4: Groceries | I4: Monthly groceries | J4: Debit Card | K4: ACC-BANK1 | L4: Supermarket | M4: No | O4: Example | P4: 46293.812 | R4: EXAMPLE ROW - delete before entering real data
A5: EX-0004 | B5: 46297 | C5: 0.36458333 | D5: Expense | E5: 350 | F5: EGP | G5: Transportation | H5: Fuel | I5: Gasoline | J5: Cash | K5: ACC-CASH | M5: No | O5: Example | P5: 46297.365 | R5: EXAMPLE ROW - delete before entering real data
A6: EX-0005 | B6: 46297 | C6: 0.36458333 | D6: Expense | E6: 120 | F6: EGP | G6: Food and Drinks | H6: Coffee | I6: Coffee | J6: Cash | K6: ACC-CASH | M6: No | O6: Example | P6: 46297.365 | R6: EXAMPLE ROW - delete before entering real data
A7: EX-0006 | B7: 46297 | C7: 0.36458333 | D7: Expense | E7: 600 | F7: EGP | G7: Household | H7: Groceries | I7: Household purchases | J7: Cash | K7: ACC-CASH | M7: No | O7: Example | P7: 46297.365 | R7: EXAMPLE ROW - delete before entering real data
A8: EX-0007 | B8: 46298 | C8: 0.5 | D8: Expense | E8: 8000 | F8: EGP | G8: Housing | H8: Rent | I8: Monthly rent | J8: Bank Transfer | K8: ACC-BANK1 | L8: Landlord | M8: Yes | N8: CMT-001 | O8: Example | P8: 46298.5 | R8: EXAMPLE ROW - delete before entering real data
A9: EX-0008 | B9: 46299 | C9: 0.88541667 | D9: Expense | E9: 450 | F9: EGP | G9: Utilities | H9: Internet | I9: Home internet | J9: InstaPay | K9: ACC-BANK1 | L9: ISP | M9: Yes | N9: CMT-002 | O9: Example | P9: 46299.885 | R9: EXAMPLE ROW - delete before entering real data
A10: EX-0009 | B10: 46300 | C10: 0.41666667 | D10: Investment Contribution | E10: 3000 | F10: EGP | G10: Investments | H10: Thndr | I10: Monthly Thndr deposit | J10: InstaPay | K10: ACC-BANK1 | L10: Thndr | M10: No | O10: Example | P10: 46300.417 | R10: EXAMPLE ROW - delete before entering real data
A11: EX-0010 | B11: 46300 | C11: 0.42013889 | D11: Savings Transfer | E11: 2000 | F11: EGP | G11: Savings | H11: Savings Account | I11: Emergency fund top-up | J11: Bank Transfer | K11: ACC-BANK1 | M11: No | O11: Example | P11: 46300.42 | R11: EXAMPLE ROW - delete before entering real data
A12: EX-0011 | B12: 46301 | C12: 0.69444444 | D12: Expense | E12: 900 | F12: EGP | G12: Shopping | H12: Clothing | I12: T-shirt | J12: Debit Card | K12: ACC-BANK1 | L12: Store | M12: No | O12: Example | P12: 46301.694 | R12: EXAMPLE ROW - delete before entering real data
A13: EX-0012 | B13: 46302 | C13: 0.47222222 | D13: Refund | E13: 300 | F13: EGP | G13: Shopping | H13: Clothing | I13: Returned T-shirt | J13: Debit Card | K13: ACC-BANK1 | L13: Store | M13: No | N13: EX-0011 | O13: Example | P13: 46302.472 | R13: EXAMPLE ROW - delete before entering real data
A14: EX-0013 | B14: 46303 | C14: 0.54166667 | D14: Internal Transfer | E14: 2000 | F14: EGP | G14: Transfers | H14: ATM Withdrawal | I14: ATM cash | J14: Cash | K14: ACC-BANK1 | M14: No | O14: Example | P14: 46303.542 | R14: EXAMPLE ROW - delete before entering real data

Sheet Commitments
A1: Commitment_ID | B1: Name | C1: Category | D1: Expected_Amount | E1: Due_Date | F1: Frequency | G1: Start_Date | H1: End_Date | I1: Active_Status | J1: Payment_Status | K1: Related_Transaction_ID | L1: Paid_This_Month | M1: Remaining_This_Month | N1: Notes
A2: CMT-001 | B2: Rent | C2: Housing | D2: 8000 | E2: 1 | F2: Monthly | G2: 46023 | I2: Active | J2: =IF(A2="","",IF(I2<>"Active","Inactive",IF(L2>=D2,"Paid",IF(L2>0,"Partial",IF(DATE(YEAR(Settings!$B$4),MONTH(Settings!$B$4),MIN(E2,DAY(EOMONTH(Settings!$B$4,0))))<TODAY(),"Overdue","Expected"))))) -> Paid | K2: EX-0007 | L2: =IF(A2="","",SUMIFS(Transactions!$E$2:$E$5000,Transactions!$N$2:$N$5000,A2,Transactions!$B$2:$B$5000,">="&Settings!$B$4,Transactions!$B$2:$B$5000,"<="&EOMONTH(Settings!$B$4,0))-SUMIFS(Transactions!$E$2:$E$5000,Transactions!$N$2:$N$5000,A2,Transactions!$D$2:$D$5000,"Refund",Transactions!$B$2:$B$5000,">="&Settings!$B$4,Transactions!$B$2:$B$5000,"<="&EOMONTH(Settings!$B$4,0))) -> 8000 | M2: =IF(A2="","",IF(I2="Active",MAX(0,D2-L2),0)) -> 0 | N2: EXAMPLE ROW - replace with your commitments
A3: CMT-002 | B3: Home internet | C3: Utilities | D3: 450 | E3: 5 | F3: Monthly | G3: 46023 | I3: Active | J3: =IF(A3="","",IF(I3<>"Active","Inactive",IF(L3>=D3,"Paid",IF(L3>0,"Partial",IF(DATE(YEAR(Settings!$B$4),MONTH(Settings!$B$4),MIN(E3,DAY(EOMONTH(Settings!$B$4,0))))<TODAY(),"Overdue","Expected"))))) -> Paid | K3: EX-0008 | L3: =IF(A3="","",SUMIFS(Transactions!$E$2:$E$5000,Transactions!$N$2:$N$5000,A3,Transactions!$B$2:$B$5000,">="&Settings!$B$4,Transactions!$B$2:$B$5000,"<="&EOMONTH(Settings!$B$4,0))-SUMIFS(Transactions!$E$2:$E$5000,Transactions!$N$2:$N$5000,A3,Transactions!$D$2:$D$5000,"Refund",Transactions!$B$2:$B$5000,">="&Settings!$B$4,Transactions!$B$2:$B$5000,"<="&EOMONTH(Settings!$B$4,0))) -> 450 | M3: =IF(A3="","",IF(I3="Active",MAX(0,D3-L3),0)) -> 0 | N3: EXAMPLE ROW - replace with your commitments
A4: CMT-003 | B4: Mobile plan | C4: Utilities | D4: 300 | E4: 10 | F4: Monthly | G4: 46023 | I4: Active | J4: =IF(A4="","",IF(I4<>"Active","Inactive",IF(L4>=D4,"Paid",IF(L4>0,"Partial",IF(DATE(YEAR(Settings!$B$4),MONTH(Settings!$B$4),MIN(E4,DAY(EOMONTH(Settings!$B$4,0))))<TODAY(),"Overdue","Expected"))))) -> Overdue | L4: =IF(A4="","",SUMIFS(Transactions!$E$2:$E$5000,Transactions!$N$2:$N$5000,A4,Transactions!$B$2:$B$5000,">="&Settings!$B$4,Transactions!$B$2:$B$5000,"<="&EOMONTH(Settings!$B$4,0))-SUMIFS(Transactions!$E$2:$E$5000,Transactions!$N$2:$N$5000,A4,Transactions!$D$2:$D$5000,"Refund",Transactions!$B$2:$B$5000,">="&Settings!$B$4,Transactions!$B$2:$B$5000,"<="&EOMONTH(Settings!$B$4,0))) -> 0 | M4: =IF(A4="","",IF(I4="Active",MAX(0,D4-L4),0)) -> 300 | N4: EXAMPLE ROW - replace with your commitments
A5: CMT-004 | B5: Car installment | C5: Installments | D5: 3500 | E5: 15 | F5: Monthly | G5: 46023 | H5: 46752 | I5: Active | J5: =IF(A5="","",IF(I5<>"Active","Inactive",IF(L5>=D5,"Paid",IF(L5>0,"Partial",IF(DATE(YEAR(Settings!$B$4),MONTH(Settings!$B$4),MIN(E5,DAY(EOMONTH(Settings!$B$4,0))))<TODAY(),"Overdue","Expected"))))) -> Expected | L5: =IF(A5="","",SUMIFS(Transactions!$E$2:$E$5000,Transactions!$N$2:$N$5000,A5,Transactions!$B$2:$B$5000,">="&Settings!$B$4,Transactions!$B$2:$B$5000,"<="&EOMONTH(Settings!$B$4,0))-SUMIFS(Transactions!$E$2:$E$5000,Transactions!$N$2:$N$5000,A5,Transactions!$D$2:$D$5000,"Refund",Transactions!$B$2:$B$5000,">="&Settings!$B$4,Transactions!$B$2:$B$5000,"<="&EOMONTH(Settings!$B$4,0))) -> 0 | M5: =IF(A5="","",IF(I5="Active",MAX(0,D5-L5),0)) -> 3500 | N5: EXAMPLE ROW - replace with your commitments
J6: =IF(A6="","",IF(I6<>"Active","Inactive",IF(L6>=D6,"Paid",IF(L6>0,"Partial",IF(DATE(YEAR(Settings!$B$4),MONTH(Settings!$B$4),MIN(E6,DAY(EOMONTH(Settings!$B$4,0))))<TODAY(),"Overdue","Expected"))))) | L6: =IF(A6="","",SUMIFS(Transactions!$E$2:$E$5000,Transactions!$N$2:$N$5000,A6,Transactions!$B$2:$B$5000,">="&Settings!$B$4,Transactions!$B$2:$B$5000,"<="&EOMONTH(Settings!$B$4,0))-SUMIFS(Transactions!$E$2:$E$5000,Transactions!$N$2:$N$5000,A6,Transactions!$D$2:$D$5000,"Refund",Transactions!$B$2:$B$5000,">="&Settings!$B$4,Transactions!$B$2:$B$5000,"<="&EOMONTH(Settings!$B$4,0))) | M6: =IF(A6="","",IF(I6="Active",MAX(0,D6-L6),0))
J7: =IF(A7="","",IF(I7<>"Active","Inactive",IF(L7>=D7,"Paid",IF(L7>0,"Partial",IF(DATE(YEAR(Settings!$B$4),MONTH(Settings!$B$4),MIN(E7,DAY(EOMONTH(Settings!$B$4,0))))<TODAY(),"Overdue","Expected"))))) | L7: =IF(A7="","",SUMIFS(Transactions!$E$2:$E$5000,Transactions!$N$2:$N$5000,A7,Transactions!$B$2:$B$5000,">="&Settings!$B$4,Transactions!$B$2:$B$5000,"<="&EOMONTH(Settings!$B$4,0))-SUMIFS(Transactions!$E$2:$E$5000,Transactions!$N$2:$N$5000,A7,Transactions!$D$2:$D$5000,"Refund",Transactions!$B$2:$B$5000,">="&Settings!$B$4,Transactions!$B$2:$B$5000,"<="&EOMONTH(Settings!$B$4,0))) | M7: =IF(A7="","",IF(I7="Active",MAX(0,D7-L7),0))
J8: =IF(A8="","",IF(I8<>"Active","Inactive",IF(L8>=D8,"Paid",IF(L8>0,"Partial",IF(DATE(YEAR(Settings!$B$4),MONTH(Settings!$B$4),MIN(E8,DAY(EOMONTH(Settings!$B$4,0))))<TODAY(),"Overdue","Expected"))))) | L8: =IF(A8="","",SUMIFS(Transactions!$E$2:$E$5000,Transactions!$N$2:$N$5000,A8,Transactions!$B$2:$B$5000,">="&Settings!$B$4,Transactions!$B$2:$B$5000,"<="&EOMONTH(Settings!$B$4,0))-SUMIFS(Transactions!$E$2:$E$5000,Transactions!$N$2:$N$5000,A8,Transactions!$D$2:$D$5000,"Refund",Transactions!$B$2:$B$5000,">="&Settings!$B$4,Transactions!$B$2:$B$5000,"<="&EOMONTH(Settings!$B$4,0))) | M8: =IF(A8="","",IF(I8="Active",MAX(0,D8-L8),0))
J9: =IF(A9="","",IF(I9<>"Active","Inactive",IF(L9>=D9,"Paid",IF(L9>0,"Partial",IF(DATE(YEAR(Settings!$B$4),MONTH(Settings!$B$4),MIN(E9,DAY(EOMONTH(Settings!$B$4,0))))<TODAY(),"Overdue","Expected"))))) | L9: =IF(A9="","",SUMIFS(Transactions!$E$2:$E$5000,Transactions!$N$2:$N$5000,A9,Transactions!$B$2:$B$5000,">="&Settings!$B$4,Transactions!$B$2:$B$5000,"<="&EOMONTH(Settings!$B$4,0))-SUMIFS(Transactions!$E$2:$E$5000,Transactions!$N$2:$N$5000,A9,Transactions!$D$2:$D$5000,"Refund",Transactions!$B$2:$B$5000,">="&Settings!$B$4,Transactions!$B$2:$B$5000,"<="&EOMONTH(Settings!$B$4,0))) | M9: =IF(A9="","",IF(I9="Active",MAX(0,D9-L9),0))
J10: =IF(A10="","",IF(I10<>"Active","Inactive",IF(L10>=D10,"Paid",IF(L10>0,"Partial",IF(DATE(YEAR(Settings!$B$4),MONTH(Settings!$B$4),MIN(E10,DAY(EOMONTH(Settings!$B$4,0))))<TODAY(),"Overdue","Expected"))))) | L10: =IF(A10="","",SUMIFS(Transactions!$E$2:$E$5000,Transactions!$N$2:$N$5000,A10,Transactions!$B$2:$B$5000,">="&Settings!$B$4,Transactions!$B$2:$B$5000,"<="&EOMONTH(Settings!$B$4,0))-SUMIFS(Transactions!$E$2:$E$5000,Transactions!$N$2:$N$5000,A10,Transactions!$D$2:$D$5000,"Refund",Transactions!$B$2:$B$5000,">="&Settings!$B$4,Transactions!$B$2:$B$5000,"<="&EOMONTH(Settings!$B$4,0))) | M10: =IF(A10="","",IF(I10="Active",MAX(0,D10-L10),0))
J11: =IF(A11="","",IF(I11<>"Active","Inactive",IF(L11>=D11,"Paid",IF(L11>0,"Partial",IF(DATE(YEAR(Settings!$B$4),MONTH(Settings!$B$4),MIN(E11,DAY(EOMONTH(Settings!$B$4,0))))<TODAY(),"Overdue","Expected"))))) | L11: =IF(A11="","",SUMIFS(Transactions!$E$2:$E$5000,Transactions!$N$2:$N$5000,A11,Transactions!$B$2:$B$5000,">="&Settings!$B$4,Transactions!$B$2:$B$5000,"<="&EOMONTH(Settings!$B$4,0))-SUMIFS(Transactions!$E$2:$E$5000,Transactions!$N$2:$N$5000,A11,Transactions!$D$2:$D$5000,"Refund",Transactions!$B$2:$B$5000,">="&Settings!$B$4,Transactions!$B$2:$B$5000,"<="&EOMONTH(Settings!$B$4,0))) | M11: =IF(A11="","",IF(I11="Active",MAX(0,D11-L11),0))
J12: =IF(A12="","",IF(I12<>"Active","Inactive",IF(L12>=D12,"Paid",IF(L12>0,"Partial",IF(DATE(YEAR(Settings!$B$4),MONTH(Settings!$B$4),MIN(E12,DAY(EOMONTH(Settings!$B$4,0))))<TODAY(),"Overdue","Expected"))))) | L12: =IF(A12="","",SUMIFS(Transactions!$E$2:$E$5000,Transactions!$N$2:$N$5000,A12,Transactions!$B$2:$B$5000,">="&Settings!$B$4,Transactions!$B$2:$B$5000,"<="&EOMONTH(Settings!$B$4,0))-SUMIFS(Transactions!$E$2:$E$5000,Transactions!$N$2:$N$5000,A12,Transactions!$D$2:$D$5000,"Refund",Transactions!$B$2:$B$5000,">="&Settings!$B$4,Transactions!$B$2:$B$5000,"<="&EOMONTH(Settings!$B$4,0))) | M12: =IF(A12="","",IF(I12="Active",MAX(0,D12-L12),0))
J13: =IF(A13="","",IF(I13<>"Active","Inactive",IF(L13>=D13,"Paid",IF(L13>0,"Partial",IF(DATE(YEAR(Settings!$B$4),MONTH(Settings!$B$4),MIN(E13,DAY(EOMONTH(Settings!$B$4,0))))<TODAY(),"Overdue","Expected"))))) | L13: =IF(A13="","",SUMIFS(Transactions!$E$2:$E$5000,Transactions!$N$2:$N$5000,A13,Transactions!$B$2:$B$5000,">="&Settings!$B$4,Transactions!$B$2:$B$5000,"<="&EOMONTH(Settings!$B$4,0))-SUMIFS(Transactions!$E$2:$E$5000,Transactions!$N$2:$N$5000,A13,Transactions!$D$2:$D$5000,"Refund",Transactions!$B$2:$B$5000,">="&Settings!$B$4,Transactions!$B$2:$B$5000,"<="&EOMONTH(Settings!$B$4,0))) | M13: =IF(A13="","",IF(I13="Active",MAX(0,D13-L13),0))
J14: =IF(A14="","",IF(I14<>"Active","Inactive",IF(L14>=D14,"Paid",IF(L14>0,"Partial",IF(DATE(YEAR(Settings!$B$4),MONTH(Settings!$B$4),MIN(E14,DAY(EOMONTH(Settings!$B$4,0))))<TODAY(),"Overdue","Expected"))))) | L14: =IF(A14="","",SUMIFS(Transactions!$E$2:$E$5000,Transactions!$N$2:$N$5000,A14,Transactions!$B$2:$B$5000,">="&Settings!$B$4,Transactions!$B$2:$B$5000,"<="&EOMONTH(Settings!$B$4,0))-SUMIFS(Transactions!$E$2:$E$5000,Transactions!$N$2:$N$5000,A14,Transactions!$D$2:$D$5000,"Refund",Transactions!$B$2:$B$5000,">="&Settings!$B$4,Transactions!$B$2:$B$5000,"<="&EOMONTH(Settings!$B$4,0))) | M14: =IF(A14="","",IF(I14="Active",MAX(0,D14-L14),0))
J15: =IF(A15="","",IF(I15<>"Active","Inactive",IF(L15>=D15,"Paid",IF(L15>0,"Partial",IF(DATE(YEAR(Settings!$B$4),MONTH(Settings!$B$4),MIN(E15,DAY(EOMONTH(Settings!$B$4,0))))<TODAY(),"Overdue","Expected"))))) | L15: =IF(A15="","",SUMIFS(Transactions!$E$2:$E$5000,Transactions!$N$2:$N$5000,A15,Transactions!$B$2:$B$5000,">="&Settings!$B$4,Transactions!$B$2:$B$5000,"<="&EOMONTH(Settings!$B$4,0))-SUMIFS(Transactions!$E$2:$E$5000,Transactions!$N$2:$N$5000,A15,Transactions!$D$2:$D$5000,"Refund",Transactions!$B$2:$B$5000,">="&Settings!$B$4,Transactions!$B$2:$B$5000,"<="&EOMONTH(Settings!$B$4,0))) | M15: =IF(A15="","",IF(I15="Active",MAX(0,D15-L15),0))
J16: =IF(A16="","",IF(I16<>"Active","Inactive",IF(L16>=D16,"Paid",IF(L16>0,"Partial",IF(DATE(YEAR(Settings!$B$4),MONTH(Settings!$B$4),MIN(E16,DAY(EOMONTH(Settings!$B$4,0))))<TODAY(),"Overdue","Expected"))))) | L16: =IF(A16="","",SUMIFS(Transactions!$E$2:$E$5000,Transactions!$N$2:$N$5000,A16,Transactions!$B$2:$B$5000,">="&Settings!$B$4,Transactions!$B$2:$B$5000,"<="&EOMONTH(Settings!$B$4,0))-SUMIFS(Transactions!$E$2:$E$5000,Transactions!$N$2:$N$5000,A16,Transactions!$D$2:$D$5000,"Refund",Transactions!$B$2:$B$5000,">="&Settings!$B$4,Transactions!$B$2:$B$5000,"<="&EOMONTH(Settings!$B$4,0))) | M16: =IF(A16="","",IF(I16="Active",MAX(0,D16-L16),0))
J17: =IF(A17="","",IF(I17<>"Active","Inactive",IF(L17>=D17,"Paid",IF(L17>0,"Partial",IF(DATE(YEAR(Settings!$B$4),MONTH(Settings!$B$4),MIN(E17,DAY(EOMONTH(Settings!$B$4,0))))<TODAY(),"Overdue","Expected"))))) | L17: =IF(A17="","",SUMIFS(Transactions!$E$2:$E$5000,Transactions!$N$2:$N$5000,A17,Transactions!$B$2:$B$5000,">="&Settings!$B$4,Transactions!$B$2:$B$5000,"<="&EOMONTH(Settings!$B$4,0))-SUMIFS(Transactions!$E$2:$E$5000,Transactions!$N$2:$N$5000,A17,Transactions!$D$2:$D$5000,"Refund",Transactions!$B$2:$B$5000,">="&Settings!$B$4,Transactions!$B$2:$B$5000,"<="&EOMONTH(Settings!$B$4,0))) | M17: =IF(A17="","",IF(I17="Active",MAX(0,D17-L17),0))
... J101: =IF(A101="","",IF(I101<>"Active","Inactive",IF(L101>=D101,"Paid",IF(L101>0,"Partial",IF(DATE(YEAR(Settings!$B$4),MONTH(Settings!$B$4),MIN(E101,DAY(EOMONTH(Settings!$B$4,0))))<TODAY(),"Overdue","Expected"))))) | L101: =IF(A101="","",SUMIFS(Transactions!$E$2:$E$5000,Transactions!$N$2:$N$5000,A101,Transactions!$B$2:$B$5000,">="&Settings!$B$4,Transactions!$B$2:$B$5000,"<="&EOMONTH(Settings!$B$4,0))-SUMIFS(Transactions!$E$2:$E$5000,Transactions!$N$2:$N$5000,A101,Transactions!$D$2:$D$5000,"Refund",Transactions!$B$2:$B$5000,">="&Settings!$B$4,Transactions!$B$2:$B$5000,"<="&EOMONTH(Settings!$B$4,0))) | M101: =IF(A101="","",IF(I101="Active",MAX(0,D101-L101),0))

Sheet Budgets
A1: Category | B1: Budgeted_Amount | C1: Actual_Amount | D1: Remaining_Budget | E1: Percent_Used | F1: Projected_Month_End | G1: Status | H1: Notes
A2: Housing | B2: 8000 | C2: =SUMIFS(Transactions!$E$2:$E$5000,Transactions!$D$2:$D$5000,"Expense",Transactions!$G$2:$G$5000,A2,Transactions!$B$2:$B$5000,">="&Settings!$B$4,Transactions!$B$2:$B$5000,"<="&EOMONTH(Settings!$B$4,0))-SUMIFS(Transactions!$E$2:$E$5000,Transactions!$D$2:$D$5000,"Refund",Transactions!$G$2:$G$5000,A2,Transactions!$B$2:$B$5000,">="&Settings!$B$4,Transactions!$B$2:$B$5000,"<="&EOMONTH(Settings!$B$4,0)) -> 8000 | D2: =B2-C2 -> 0 | E2: =IF(B2=0,0,C2/B2) -> 1 | F2: =IF(Summary!$B$6=0,0,C2/Summary!$B$6*Summary!$B$5) -> 20666.667 | G2: =IF(B2=0,IF(C2>0,"No budget","-"),IF(E2>1,"Over",IF(E2>=Settings!$B$9,"Warning","OK"))) -> Warning | H2: Budgeted amounts are EXAMPLES - set your own in the yellow cells.
A3: Utilities | B3: 1200 | C3: =SUMIFS(Transactions!$E$2:$E$5000,Transactions!$D$2:$D$5000,"Expense",Transactions!$G$2:$G$5000,A3,Transactions!$B$2:$B$5000,">="&Settings!$B$4,Transactions!$B$2:$B$5000,"<="&EOMONTH(Settings!$B$4,0))-SUMIFS(Transactions!$E$2:$E$5000,Transactions!$D$2:$D$5000,"Refund",Transactions!$G$2:$G$5000,A3,Transactions!$B$2:$B$5000,">="&Settings!$B$4,Transactions!$B$2:$B$5000,"<="&EOMONTH(Settings!$B$4,0)) -> 450 | D3: =B3-C3 -> 750 | E3: =IF(B3=0,0,C3/B3) -> 0.375 | F3: =IF(Summary!$B$6=0,0,C3/Summary!$B$6*Summary!$B$5) -> 1162.5 | G3: =IF(B3=0,IF(C3>0,"No budget","-"),IF(E3>1,"Over",IF(E3>=Settings!$B$9,"Warning","OK"))) -> OK | H3: Actual = Expenses minus Refunds in Report_Month (Settings).
A4: Transportation | B4: 2500 | C4: =SUMIFS(Transactions!$E$2:$E$5000,Transactions!$D$2:$D$5000,"Expense",Transactions!$G$2:$G$5000,A4,Transactions!$B$2:$B$5000,">="&Settings!$B$4,Transactions!$B$2:$B$5000,"<="&EOMONTH(Settings!$B$4,0))-SUMIFS(Transactions!$E$2:$E$5000,Transactions!$D$2:$D$5000,"Refund",Transactions!$G$2:$G$5000,A4,Transactions!$B$2:$B$5000,">="&Settings!$B$4,Transactions!$B$2:$B$5000,"<="&EOMONTH(Settings!$B$4,0)) -> 350 | D4: =B4-C4 -> 2150 | E4: =IF(B4=0,0,C4/B4) -> 0.14 | F4: =IF(Summary!$B$6=0,0,C4/Summary!$B$6*Summary!$B$5) -> 904.16667 | G4: =IF(B4=0,IF(C4>0,"No budget","-"),IF(E4>1,"Over",IF(E4>=Settings!$B$9,"Warning","OK"))) -> OK | H4: Projected = Actual / days elapsed x days in month (straight-line).
A5: Food and Drinks | B5: 2500 | C5: =SUMIFS(Transactions!$E$2:$E$5000,Transactions!$D$2:$D$5000,"Expense",Transactions!$G$2:$G$5000,A5,Transactions!$B$2:$B$5000,">="&Settings!$B$4,Transactions!$B$2:$B$5000,"<="&EOMONTH(Settings!$B$4,0))-SUMIFS(Transactions!$E$2:$E$5000,Transactions!$D$2:$D$5000,"Refund",Transactions!$G$2:$G$5000,A5,Transactions!$B$2:$B$5000,">="&Settings!$B$4,Transactions!$B$2:$B$5000,"<="&EOMONTH(Settings!$B$4,0)) -> 120 | D5: =B5-C5 -> 2380 | E5: =IF(B5=0,0,C5/B5) -> 0.048 | F5: =IF(Summary!$B$6=0,0,C5/Summary!$B$6*Summary!$B$5) -> 310 | G5: =IF(B5=0,IF(C5>0,"No budget","-"),IF(E5>1,"Over",IF(E5>=Settings!$B$9,"Warning","OK"))) -> OK
A6: Household | B6: 5000 | C6: =SUMIFS(Transactions!$E$2:$E$5000,Transactions!$D$2:$D$5000,"Expense",Transactions!$G$2:$G$5000,A6,Transactions!$B$2:$B$5000,">="&Settings!$B$4,Transactions!$B$2:$B$5000,"<="&EOMONTH(Settings!$B$4,0))-SUMIFS(Transactions!$E$2:$E$5000,Transactions!$D$2:$D$5000,"Refund",Transactions!$G$2:$G$5000,A6,Transactions!$B$2:$B$5000,">="&Settings!$B$4,Transactions!$B$2:$B$5000,"<="&EOMONTH(Settings!$B$4,0)) -> 600 | D6: =B6-C6 -> 4400 | E6: =IF(B6=0,0,C6/B6) -> 0.12 | F6: =IF(Summary!$B$6=0,0,C6/Summary!$B$6*Summary!$B$5) -> 1550 | G6: =IF(B6=0,IF(C6>0,"No budget","-"),IF(E6>1,"Over",IF(E6>=Settings!$B$9,"Warning","OK"))) -> OK
A7: Health | B7: 1000 | C7: =SUMIFS(Transactions!$E$2:$E$5000,Transactions!$D$2:$D$5000,"Expense",Transactions!$G$2:$G$5000,A7,Transactions!$B$2:$B$5000,">="&Settings!$B$4,Transactions!$B$2:$B$5000,"<="&EOMONTH(Settings!$B$4,0))-SUMIFS(Transactions!$E$2:$E$5000,Transactions!$D$2:$D$5000,"Refund",Transactions!$G$2:$G$5000,A7,Transactions!$B$2:$B$5000,">="&Settings!$B$4,Transactions!$B$2:$B$5000,"<="&EOMONTH(Settings!$B$4,0)) -> 0 | D7: =B7-C7 -> 1000 | E7: =IF(B7=0,0,C7/B7) -> 0 | F7: =IF(Summary!$B$6=0,0,C7/Summary!$B$6*Summary!$B$5) -> 0 | G7: =IF(B7=0,IF(C7>0,"No budget","-"),IF(E7>1,"Over",IF(E7>=Settings!$B$9,"Warning","OK"))) -> OK
A8: Personal Care | B8: 500 | C8: =SUMIFS(Transactions!$E$2:$E$5000,Transactions!$D$2:$D$5000,"Expense",Transactions!$G$2:$G$5000,A8,Transactions!$B$2:$B$5000,">="&Settings!$B$4,Transactions!$B$2:$B$5000,"<="&EOMONTH(Settings!$B$4,0))-SUMIFS(Transactions!$E$2:$E$5000,Transactions!$D$2:$D$5000,"Refund",Transactions!$G$2:$G$5000,A8,Transactions!$B$2:$B$5000,">="&Settings!$B$4,Transactions!$B$2:$B$5000,"<="&EOMONTH(Settings!$B$4,0)) -> 0 | D8: =B8-C8 -> 500 | E8: =IF(B8=0,0,C8/B8) -> 0 | F8: =IF(Summary!$B$6=0,0,C8/Summary!$B$6*Summary!$B$5) -> 0 | G8: =IF(B8=0,IF(C8>0,"No budget","-"),IF(E8>1,"Over",IF(E8>=Settings!$B$9,"Warning","OK"))) -> OK
A9: Shopping | B9: 1500 | C9: =SUMIFS(Transactions!$E$2:$E$5000,Transactions!$D$2:$D$5000,"Expense",Transactions!$G$2:$G$5000,A9,Transactions!$B$2:$B$5000,">="&Settings!$B$4,Transactions!$B$2:$B$5000,"<="&EOMONTH(Settings!$B$4,0))-SUMIFS(Transactions!$E$2:$E$5000,Transactions!$D$2:$D$5000,"Refund",Transactions!$G$2:$G$5000,A9,Transactions!$B$2:$B$5000,">="&Settings!$B$4,Transactions!$B$2:$B$5000,"<="&EOMONTH(Settings!$B$4,0)) -> 600 | D9: =B9-C9 -> 900 | E9: =IF(B9=0,0,C9/B9) -> 0.4 | F9: =IF(Summary!$B$6=0,0,C9/Summary!$B$6*Summary!$B$5) -> 1550 | G9: =IF(B9=0,IF(C9>0,"No budget","-"),IF(E9>1,"Over",IF(E9>=Settings!$B$9,"Warning","OK"))) -> OK
A10: Entertainment | B10: 1000 | C10: =SUMIFS(Transactions!$E$2:$E$5000,Transactions!$D$2:$D$5000,"Expense",Transactions!$G$2:$G$5000,A10,Transactions!$B$2:$B$5000,">="&Settings!$B$4,Transactions!$B$2:$B$5000,"<="&EOMONTH(Settings!$B$4,0))-SUMIFS(Transactions!$E$2:$E$5000,Transactions!$D$2:$D$5000,"Refund",Transactions!$G$2:$G$5000,A10,Transactions!$B$2:$B$5000,">="&Settings!$B$4,Transactions!$B$2:$B$5000,"<="&EOMONTH(Settings!$B$4,0)) -> 0 | D10: =B10-C10 -> 1000 | E10: =IF(B10=0,0,C10/B10) -> 0 | F10: =IF(Summary!$B$6=0,0,C10/Summary!$B$6*Summary!$B$5) -> 0 | G10: =IF(B10=0,IF(C10>0,"No budget","-"),IF(E10>1,"Over",IF(E10>=Settings!$B$9,"Warning","OK"))) -> OK
A11: Education | B11: 500 | C11: =SUMIFS(Transactions!$E$2:$E$5000,Transactions!$D$2:$D$5000,"Expense",Transactions!$G$2:$G$5000,A11,Transactions!$B$2:$B$5000,">="&Settings!$B$4,Transactions!$B$2:$B$5000,"<="&EOMONTH(Settings!$B$4,0))-SUMIFS(Transactions!$E$2:$E$5000,Transactions!$D$2:$D$5000,"Refund",Transactions!$G$2:$G$5000,A11,Transactions!$B$2:$B$5000,">="&Settings!$B$4,Transactions!$B$2:$B$5000,"<="&EOMONTH(Settings!$B$4,0)) -> 0 | D11: =B11-C11 -> 500 | E11: =IF(B11=0,0,C11/B11) -> 0 | F11: =IF(Summary!$B$6=0,0,C11/Summary!$B$6*Summary!$B$5) -> 0 | G11: =IF(B11=0,IF(C11>0,"No budget","-"),IF(E11>1,"Over",IF(E11>=Settings!$B$9,"Warning","OK"))) -> OK
A12: Family and Gifts | B12: 1000 | C12: =SUMIFS(Transactions!$E$2:$E$5000,Transactions!$D$2:$D$5000,"Expense",Transactions!$G$2:$G$5000,A12,Transactions!$B$2:$B$5000,">="&Settings!$B$4,Transactions!$B$2:$B$5000,"<="&EOMONTH(Settings!$B$4,0))-SUMIFS(Transactions!$E$2:$E$5000,Transactions!$D$2:$D$5000,"Refund",Transactions!$G$2:$G$5000,A12,Transactions!$B$2:$B$5000,">="&Settings!$B$4,Transactions!$B$2:$B$5000,"<="&EOMONTH(Settings!$B$4,0)) -> 0 | D12: =B12-C12 -> 1000 | E12: =IF(B12=0,0,C12/B12) -> 0 | F12: =IF(Summary!$B$6=0,0,C12/Summary!$B$6*Summary!$B$5) -> 0 | G12: =IF(B12=0,IF(C12>0,"No budget","-"),IF(E12>1,"Over",IF(E12>=Settings!$B$9,"Warning","OK"))) -> OK
A13: Charity | B13: 500 | C13: =SUMIFS(Transactions!$E$2:$E$5000,Transactions!$D$2:$D$5000,"Expense",Transactions!$G$2:$G$5000,A13,Transactions!$B$2:$B$5000,">="&Settings!$B$4,Transactions!$B$2:$B$5000,"<="&EOMONTH(Settings!$B$4,0))-SUMIFS(Transactions!$E$2:$E$5000,Transactions!$D$2:$D$5000,"Refund",Transactions!$G$2:$G$5000,A13,Transactions!$B$2:$B$5000,">="&Settings!$B$4,Transactions!$B$2:$B$5000,"<="&EOMONTH(Settings!$B$4,0)) -> 0 | D13: =B13-C13 -> 500 | E13: =IF(B13=0,0,C13/B13) -> 0 | F13: =IF(Summary!$B$6=0,0,C13/Summary!$B$6*Summary!$B$5) -> 0 | G13: =IF(B13=0,IF(C13>0,"No budget","-"),IF(E13>1,"Over",IF(E13>=Settings!$B$9,"Warning","OK"))) -> OK
A14: Installments | B14: 3500 | C14: =SUMIFS(Transactions!$E$2:$E$5000,Transactions!$D$2:$D$5000,"Expense",Transactions!$G$2:$G$5000,A14,Transactions!$B$2:$B$5000,">="&Settings!$B$4,Transactions!$B$2:$B$5000,"<="&EOMONTH(Settings!$B$4,0))-SUMIFS(Transactions!$E$2:$E$5000,Transactions!$D$2:$D$5000,"Refund",Transactions!$G$2:$G$5000,A14,Transactions!$B$2:$B$5000,">="&Settings!$B$4,Transactions!$B$2:$B$5000,"<="&EOMONTH(Settings!$B$4,0)) -> 0 | D14: =B14-C14 -> 3500 | E14: =IF(B14=0,0,C14/B14) -> 0 | F14: =IF(Summary!$B$6=0,0,C14/Summary!$B$6*Summary!$B$5) -> 0 | G14: =IF(B14=0,IF(C14>0,"No budget","-"),IF(E14>1,"Over",IF(E14>=Settings!$B$9,"Warning","OK"))) -> OK
A15: Fees and Charges | B15: 200 | C15: =SUMIFS(Transactions!$E$2:$E$5000,Transactions!$D$2:$D$5000,"Expense",Transactions!$G$2:$G$5000,A15,Transactions!$B$2:$B$5000,">="&Settings!$B$4,Transactions!$B$2:$B$5000,"<="&EOMONTH(Settings!$B$4,0))-SUMIFS(Transactions!$E$2:$E$5000,Transactions!$D$2:$D$5000,"Refund",Transactions!$G$2:$G$5000,A15,Transactions!$B$2:$B$5000,">="&Settings!$B$4,Transactions!$B$2:$B$5000,"<="&EOMONTH(Settings!$B$4,0)) -> 0 | D15: =B15-C15 -> 200 | E15: =IF(B15=0,0,C15/B15) -> 0 | F15: =IF(Summary!$B$6=0,0,C15/Summary!$B$6*Summary!$B$5) -> 0 | G15: =IF(B15=0,IF(C15>0,"No budget","-"),IF(E15>1,"Over",IF(E15>=Settings!$B$9,"Warning","OK"))) -> OK
A16: Other | B16: 500 | C16: =SUMIFS(Transactions!$E$2:$E$5000,Transactions!$D$2:$D$5000,"Expense",Transactions!$G$2:$G$5000,A16,Transactions!$B$2:$B$5000,">="&Settings!$B$4,Transactions!$B$2:$B$5000,"<="&EOMONTH(Settings!$B$4,0))-SUMIFS(Transactions!$E$2:$E$5000,Transactions!$D$2:$D$5000,"Refund",Transactions!$G$2:$G$5000,A16,Transactions!$B$2:$B$5000,">="&Settings!$B$4,Transactions!$B$2:$B$5000,"<="&EOMONTH(Settings!$B$4,0)) -> 0 | D16: =B16-C16 -> 500 | E16: =IF(B16=0,0,C16/B16) -> 0 | F16: =IF(Summary!$B$6=0,0,C16/Summary!$B$6*Summary!$B$5) -> 0 | G16: =IF(B16=0,IF(C16>0,"No budget","-"),IF(E16>1,"Over",IF(E16>=Settings!$B$9,"Warning","OK"))) -> OK
A17: TOTAL | B17: =SUM(B2:B16) -> 29400 | C17: =SUM(C2:C16) -> 10120 | D17: =SUM(D2:D16) -> 19280 | E17: =IF(B17=0,0,C17/B17) -> 0.34421769 | F17: =SUM(F2:F16) -> 26143.333

Sheet Accounts
A1: Account_ID | B1: Account_Name | C1: Account_Type | D1: Institution | E1: Currency | F1: Opening_Balance | G1: Opening_Date | H1: Last_Reconciled_Balance | I1: Reconciled_Date | J1: Include_In_Cash | K1: Active | L1: Notes
A2: ACC-CASH | B2: Wallet cash | C2: Cash | E2: EGP | F2: 0 | G2: 46296 | H2: 0 | I2: 46296 | J2: Yes | K2: Active | L2: EXAMPLE ROW - rename and set balances
A3: ACC-BANK1 | B3: Main bank account | C3: Bank Account | D3: Your bank | E3: EGP | F3: 0 | G3: 46296 | H3: 0 | I3: 46296 | J3: Yes | K3: Active | L3: EXAMPLE ROW - rename and set balances
A4: ACC-THNDR | B4: Thndr | C4: Investment | D4: Thndr | E4: EGP | F4: 0 | G4: 46296 | H4: 0 | I4: 46296 | J4: No | K4: Active | L4: EXAMPLE ROW - rename and set balances

Sheet Investment_Transactions
A1: Inv_Txn_ID | B1: Date | C1: Event_Type | D1: Asset_Name | E1: Ticker | F1: Quantity | G1: Price_Per_Unit | H1: Gross_Amount | I1: Fees | J1: Net_Amount | K1: Currency | L1: Related_Transaction_ID | M1: Notes
A2: INV-0001 | B2: 46300 | C2: Contribution | D2: Cash deposit | H2: 3000 | I2: 0 | J2: =IF(C2="","",IF(OR(C2="Purchase",C2="Fee",C2="Withdrawal"),-(H2+I2),H2-I2)) -> 3000 | K2: EGP | L2: EX-0009 | M2: EXAMPLE ROW
A3: INV-0002 | B3: 46301 | C3: Purchase | D3: Example Money Market Fund | F3: 1500 | G3: 1 | H3: 1500 | I3: 0 | J3: =IF(C3="","",IF(OR(C3="Purchase",C3="Fee",C3="Withdrawal"),-(H3+I3),H3-I3)) -> -1500 | K3: EGP | M3: EXAMPLE ROW
A4: INV-0003 | B4: 46301 | C4: Purchase | D4: Example Stock | E4: EXMP | F4: 100 | G4: 14.5 | H4: 1450 | I4: 7.25 | J4: =IF(C4="","",IF(OR(C4="Purchase",C4="Fee",C4="Withdrawal"),-(H4+I4),H4-I4)) -> -1457.25 | K4: EGP | M4: EXAMPLE ROW
J5: =IF(C5="","",IF(OR(C5="Purchase",C5="Fee",C5="Withdrawal"),-(H5+I5),H5-I5))
J6: =IF(C6="","",IF(OR(C6="Purchase",C6="Fee",C6="Withdrawal"),-(H6+I6),H6-I6))
J7: =IF(C7="","",IF(OR(C7="Purchase",C7="Fee",C7="Withdrawal"),-(H7+I7),H7-I7))
J8: =IF(C8="","",IF(OR(C8="Purchase",C8="Fee",C8="Withdrawal"),-(H8+I8),H8-I8))
J9: =IF(C9="","",IF(OR(C9="Purchase",C9="Fee",C9="Withdrawal"),-(H9+I9),H9-I9))
J10: =IF(C10="","",IF(OR(C10="Purchase",C10="Fee",C10="Withdrawal"),-(H10+I10),H10-I10))
J11: =IF(C11="","",IF(OR(C11="Purchase",C11="Fee",C11="Withdrawal"),-(H11+I11),H11-I11))
J12: =IF(C12="","",IF(OR(C12="Purchase",C12="Fee",C12="Withdrawal"),-(H12+I12),H12-I12))
J13: =IF(C13="","",IF(OR(C13="Purchase",C13="Fee",C13="Withdrawal"),-(H13+I13),H13-I13))
J14: =IF(C14="","",IF(OR(C14="Purchase",C14="Fee",C14="Withdrawal"),-(H14+I14),H14-I14))
J15: =IF(C15="","",IF(OR(C15="Purchase",C15="Fee",C15="Withdrawal"),-(H15+I15),H15-I15))
J16: =IF(C16="","",IF(OR(C16="Purchase",C16="Fee",C16="Withdrawal"),-(H16+I16),H16-I16))
... J1001: =IF(C1001="","",IF(OR(C1001="Purchase",C1001="Fee",C1001="Withdrawal"),-(H1001+I1001),H1001-I1001))

Sheet Holdings
A1: Asset_Name | B1: Product_Type | C1: Ticker | D1: Quantity | E1: Avg_Acquisition_Cost | F1: Cost_Basis | G1: Current_Price | H1: Current_Market_Value | I1: Unrealized_Gain_Loss | J1: Gain_Loss_Pct | K1: Valuation_Date | L1: Fees_Paid | M1: Valuation_Source | N1: Value_Status | O1: Currency | P1: Notes
A2: Example Money Market Fund | B2: Money Market Fund | D2: 1500 | E2: 1 | F2: =IF(A2="","",D2*E2) -> 1500 | G2: 1.02 | H2: =IF(A2="","",D2*G2) -> 1530 | I2: =IF(A2="","",H2-F2) -> 30 | J2: =IF(OR(A2="",F2=0),"",I2/F2) -> 0.02 | K2: 46305 | L2: 0 | M2: Thndr app | N2: Actual | O2: EGP | P2: EXAMPLE ROW - replace with your Thndr holdings
A3: Example Stock | B3: Stock | C3: EXMP | D3: 100 | E3: 14.5725 | F3: =IF(A3="","",D3*E3) -> 1457.25 | G3: 15.1 | H3: =IF(A3="","",D3*G3) -> 1510 | I3: =IF(A3="","",H3-F3) -> 52.75 | J3: =IF(OR(A3="",F3=0),"",I3/F3) -> 0.036198319 | K3: 46305 | L3: 7.25 | M3: Thndr app | N3: Actual | O3: EGP | P3: EXAMPLE ROW - replace with your Thndr holdings
F4: =IF(A4="","",D4*E4) | H4: =IF(A4="","",D4*G4) | I4: =IF(A4="","",H4-F4) | J4: =IF(OR(A4="",F4=0),"",I4/F4)
F5: =IF(A5="","",D5*E5) | H5: =IF(A5="","",D5*G5) | I5: =IF(A5="","",H5-F5) | J5: =IF(OR(A5="",F5=0),"",I5/F5)
F6: =IF(A6="","",D6*E6) | H6: =IF(A6="","",D6*G6) | I6: =IF(A6="","",H6-F6) | J6: =IF(OR(A6="",F6=0),"",I6/F6)
F7: =IF(A7="","",D7*E7) | H7: =IF(A7="","",D7*G7) | I7: =IF(A7="","",H7-F7) | J7: =IF(OR(A7="",F7=0),"",I7/F7)
F8: =IF(A8="","",D8*E8) | H8: =IF(A8="","",D8*G8) | I8: =IF(A8="","",H8-F8) | J8: =IF(OR(A8="",F8=0),"",I8/F8)
F9: =IF(A9="","",D9*E9) | H9: =IF(A9="","",D9*G9) | I9: =IF(A9="","",H9-F9) | J9: =IF(OR(A9="",F9=0),"",I9/F9)
F10: =IF(A10="","",D10*E10) | H10: =IF(A10="","",D10*G10) | I10: =IF(A10="","",H10-F10) | J10: =IF(OR(A10="",F10=0),"",I10/F10)
F11: =IF(A11="","",D11*E11) | H11: =IF(A11="","",D11*G11) | I11: =IF(A11="","",H11-F11) | J11: =IF(OR(A11="",F11=0),"",I11/F11)
F12: =IF(A12="","",D12*E12) | H12: =IF(A12="","",D12*G12) | I12: =IF(A12="","",H12-F12) | J12: =IF(OR(A12="",F12=0),"",I12/F12)
F13: =IF(A13="","",D13*E13) | H13: =IF(A13="","",D13*G13) | I13: =IF(A13="","",H13-F13) | J13: =IF(OR(A13="",F13=0),"",I13/F13)
F14: =IF(A14="","",D14*E14) | H14: =IF(A14="","",D14*G14) | I14: =IF(A14="","",H14-F14) | J14: =IF(OR(A14="",F14=0),"",I14/F14)
F15: =IF(A15="","",D15*E15) | H15: =IF(A15="","",D15*G15) | I15: =IF(A15="","",H15-F15) | J15: =IF(OR(A15="",F15=0),"",I15/F15)
... F101: =IF(A101="","",D101*E101) | H101: =IF(A101="","",D101*G101) | I101: =IF(A101="","",H101-F101) | J101: =IF(OR(A101="",F101=0),"",I101/F101)
A103: TOTAL | F103: =SUM(F2:F101) -> 2957.25 | H103: =SUM(H2:H101) -> 3040 | I103: =SUM(I2:I101) -> 82.75 | J103: =IF(F103=0,0,I103/F103) -> 0.027982078

Sheet Goals
A1: Goal_ID | B1: Goal_Name | C1: Target_Amount | D1: Current_Amount | E1: Target_Date | F1: Priority | G1: Months_Remaining | H1: Required_Monthly_Contribution | I1: Progress_Pct | J1: Notes
A2: GOAL-01 | B2: Emergency fund | C2: 150000 | D2: 20000 | E2: 46752 | F2: High | G2: =IF(A2="","",MAX(0,(YEAR(E2)-YEAR(TODAY()))*12+MONTH(E2)-MONTH(TODAY()))) -> 14 | H2: =IF(A2="","",IF(G2=0,MAX(0,C2-D2),MAX(0,C2-D2)/G2)) -> 9285.7143 | I2: =IF(OR(A2="",C2=0),"",MIN(1,D2/C2)) -> 0.13333333 | J2: EXAMPLE ROW
A3: GOAL-02 | B3: Car down payment | C3: 200000 | D3: 15000 | E3: 46934 | F3: Medium | G3: =IF(A3="","",MAX(0,(YEAR(E3)-YEAR(TODAY()))*12+MONTH(E3)-MONTH(TODAY()))) -> 20 | H3: =IF(A3="","",IF(G3=0,MAX(0,C3-D3),MAX(0,C3-D3)/G3)) -> 9250 | I3: =IF(OR(A3="",C3=0),"",MIN(1,D3/C3)) -> 0.075 | J3: EXAMPLE ROW
G4: =IF(A4="","",MAX(0,(YEAR(E4)-YEAR(TODAY()))*12+MONTH(E4)-MONTH(TODAY()))) | H4: =IF(A4="","",IF(G4=0,MAX(0,C4-D4),MAX(0,C4-D4)/G4)) | I4: =IF(OR(A4="",C4=0),"",MIN(1,D4/C4))
G5: =IF(A5="","",MAX(0,(YEAR(E5)-YEAR(TODAY()))*12+MONTH(E5)-MONTH(TODAY()))) | H5: =IF(A5="","",IF(G5=0,MAX(0,C5-D5),MAX(0,C5-D5)/G5)) | I5: =IF(OR(A5="",C5=0),"",MIN(1,D5/C5))
G6: =IF(A6="","",MAX(0,(YEAR(E6)-YEAR(TODAY()))*12+MONTH(E6)-MONTH(TODAY()))) | H6: =IF(A6="","",IF(G6=0,MAX(0,C6-D6),MAX(0,C6-D6)/G6)) | I6: =IF(OR(A6="",C6=0),"",MIN(1,D6/C6))
G7: =IF(A7="","",MAX(0,(YEAR(E7)-YEAR(TODAY()))*12+MONTH(E7)-MONTH(TODAY()))) | H7: =IF(A7="","",IF(G7=0,MAX(0,C7-D7),MAX(0,C7-D7)/G7)) | I7: =IF(OR(A7="",C7=0),"",MIN(1,D7/C7))
G8: =IF(A8="","",MAX(0,(YEAR(E8)-YEAR(TODAY()))*12+MONTH(E8)-MONTH(TODAY()))) | H8: =IF(A8="","",IF(G8=0,MAX(0,C8-D8),MAX(0,C8-D8)/G8)) | I8: =IF(OR(A8="",C8=0),"",MIN(1,D8/C8))
G9: =IF(A9="","",MAX(0,(YEAR(E9)-YEAR(TODAY()))*12+MONTH(E9)-MONTH(TODAY()))) | H9: =IF(A9="","",IF(G9=0,MAX(0,C9-D9),MAX(0,C9-D9)/G9)) | I9: =IF(OR(A9="",C9=0),"",MIN(1,D9/C9))
G10: =IF(A10="","",MAX(0,(YEAR(E10)-YEAR(TODAY()))*12+MONTH(E10)-MONTH(TODAY()))) | H10: =IF(A10="","",IF(G10=0,MAX(0,C10-D10),MAX(0,C10-D10)/G10)) | I10: =IF(OR(A10="",C10=0),"",MIN(1,D10/C10))
G11: =IF(A11="","",MAX(0,(YEAR(E11)-YEAR(TODAY()))*12+MONTH(E11)-MONTH(TODAY()))) | H11: =IF(A11="","",IF(G11=0,MAX(0,C11-D11),MAX(0,C11-D11)/G11)) | I11: =IF(OR(A11="",C11=0),"",MIN(1,D11/C11))
G12: =IF(A12="","",MAX(0,(YEAR(E12)-YEAR(TODAY()))*12+MONTH(E12)-MONTH(TODAY()))) | H12: =IF(A12="","",IF(G12=0,MAX(0,C12-D12),MAX(0,C12-D12)/G12)) | I12: =IF(OR(A12="",C12=0),"",MIN(1,D12/C12))
G13: =IF(A13="","",MAX(0,(YEAR(E13)-YEAR(TODAY()))*12+MONTH(E13)-MONTH(TODAY()))) | H13: =IF(A13="","",IF(G13=0,MAX(0,C13-D13),MAX(0,C13-D13)/G13)) | I13: =IF(OR(A13="",C13=0),"",MIN(1,D13/C13))
G14: =IF(A14="","",MAX(0,(YEAR(E14)-YEAR(TODAY()))*12+MONTH(E14)-MONTH(TODAY()))) | H14: =IF(A14="","",IF(G14=0,MAX(0,C14-D14),MAX(0,C14-D14)/G14)) | I14: =IF(OR(A14="",C14=0),"",MIN(1,D14/C14))
G15: =IF(A15="","",MAX(0,(YEAR(E15)-YEAR(TODAY()))*12+MONTH(E15)-MONTH(TODAY()))) | H15: =IF(A15="","",IF(G15=0,MAX(0,C15-D15),MAX(0,C15-D15)/G15)) | I15: =IF(OR(A15="",C15=0),"",MIN(1,D15/C15))
... G51: =IF(A51="","",MAX(0,(YEAR(E51)-YEAR(TODAY()))*12+MONTH(E51)-MONTH(TODAY()))) | H51: =IF(A51="","",IF(G51=0,MAX(0,C51-D51),MAX(0,C51-D51)/G51)) | I51: =IF(OR(A51="",C51=0),"",MIN(1,D51/C51))

Sheet Monthly_Snapshots
A1: Month | B1: Total_Income | C1: Salary | D1: Additional_Income | E1: Net_Consumption | F1: Fixed_Commitments | G1: Variable_Expenses | H1: Debt_Payments | I1: Savings_Transfers | J1: Investment_Contributions | K1: Investment_Withdrawals | L1: Savings_Rate | M1: Saved_Invested_Rate | N1: Portfolio_Value | O1: Cash_Balance | P1: Net_Worth | Q1: Snapshot_Created_At | R1: Notes
R2: Filled automatically at month-end (Phase 3) with frozen values, so past reports never change. Leave empty for now.

Sheet Lists
A1: Transaction_Type | B1: Payment_Method | C1: Source | D1: Currency | E1: Yes_No | F1: Category | H1: Category | I1: Subcategory | K1: Inv_Event_Type | L1: Product_Type | M1: Value_Status | N1: Active_Status | O1: Frequency | P1: Priority | Q1: Account_Type
A2: Income | B2: Cash | C2: Manual | D2: EGP | E2: Yes | F2: Housing | H2: Housing | I2: Rent | K2: Contribution | L2: Stock | M2: Actual | N2: Active | O2: Monthly | P2: High | Q2: Cash
A3: Expense | B3: Debit Card | C3: Telegram | D3: USD | E3: No | F3: Utilities | H3: Housing | I3: Maintenance | K3: Withdrawal | L3: Equity Fund | M3: Estimate | N3: Paused | O3: Quarterly | P3: Medium | Q3: Bank Account
A4: Refund | B4: Credit Card | C4: Voice | D4: EUR | F4: Transportation | H4: Housing | I4: Furniture | K4: Purchase | L4: Money Market Fund | N4: Ended | O4: Yearly | P4: Low | Q4: Mobile Wallet
A5: Debt Payment | B5: InstaPay | C5: Import | D5: SAR | F5: Food and Drinks | H5: Utilities | I5: Electricity | K5: Sale | L5: Fixed Income Fund | Q5: Credit Card
A6: Savings Transfer | B6: Mobile Wallet | C6: Example | D6: AED | F6: Household | H6: Utilities | I6: Water | K6: Fee | L6: Gold Fund | Q6: Investment
A7: Investment Contribution | B7: Bank Transfer | F7: Health | H7: Utilities | I7: Gas | K7: Dividend | L7: Gold | Q7: Savings
A8: Investment Withdrawal | B8: Other | F8: Personal Care | H8: Utilities | I8: Internet | K8: Distribution | L8: T-Bill
A9: Investment Return | F9: Shopping | H9: Utilities | I9: Mobile | K9: Interest | L9: Other
A10: Internal Transfer | F10: Entertainment | H10: Transportation | I10: Fuel
F11: Education | H11: Transportation | I11: Ride-hailing
F12: Family and Gifts | H12: Transportation | I12: Public Transport
F13: Charity | H13: Transportation | I13: Car Maintenance
F14: Installments | H14: Transportation | I14: Parking
F15: Fees and Charges | H15: Food and Drinks | I15: Restaurants
F16: Other | H16: Food and Drinks | I16: Coffee
F17: Salary | H17: Food and Drinks | I17: Delivery
F18: Additional Income | H18: Food and Drinks | I18: Snacks
F19: Savings | H19: Household | I19: Groceries
F20: Investments | H20: Household | I20: Cleaning Supplies
F21: Debt | H21: Household | I21: Home Items
F22: Transfers | H22: Health | I22: Pharmacy
H23: Health | I23: Doctor
H24: Health | I24: Lab Tests
H25: Health | I25: Insurance
H26: Personal Care | I26: Haircut
H27: Personal Care | I27: Cosmetics
H28: Shopping | I28: Clothing
H29: Shopping | I29: Electronics
H30: Shopping | I30: Accessories
H31: Entertainment | I31: Outings
H32: Entertainment | I32: Subscriptions
H33: Entertainment | I33: Travel
H34: Education | I34: Courses
... H57: Transfers | I57: ATM Withdrawal
